{
  "name": "Ouă Umplute Asiatice pe Covrigei Crocanti",
  "instructions": "1. Tăiați cu grijă fiecare ou fiert în jumătate pe lungime. Scoateți delicat gălbenușurile și puneți-le într-un robot de bucătărie sau blender. Păstrați albușurile pentru altă utilizare, cum ar fi o salată sau umplutură pentru sandvișuri.\n\n2. La gălbenușuri, adăugați maioneză, sos de soia, pastă de wasabi, ghimbir proaspăt și oțet de orez. Procesați amestecul la viteză medie până devine complet neted și cremos, răzuind laturile după necesitate pentru a asigura o mixare uniformă.\n\n3. Adăugați pesmetul panko la amestecul de gălbenușuri și pulsați de câteva ori până când pesmetul este complet încorporat și amestecul are o consistență ușor texturată.\n\n4. Transferați amestecul de gălbenușuri într-o pungă de dresaj cu vârf decorativ, sau pur și simplu folosiți o lingură sau cuțit pentru a întinde amestecul generos pe fiecare covrig crocant, creând un strat uniform.\n\n5. Decorați fiecare covrig crocant cu o presărare ușoară de semințe de susan negru și ceapă verde tăiată subțire pentru culoare, textură și o notă proaspătă de ceapă.\n\n6. Dacă nu serviți imediat, acoperiți ușor și refrigerați covrigii crocanti pregătiți până la 3 ore pentru a-i menține proaspeți și a permite aromelor să se îmbine. Serviți răciți sau la temperatura camerei.",
  "simpleInstructions": "1. Scoateți gălbenușurile și mixați-le cu maioneză și condimente asiatice.\n\n2. Procesați până devine neted și cremos.\n\n3. Pulsați pesmetul panko pentru textură.\n\n4. Dresați sau întindeți amestecul pe covrigii crocanti.\n\n5. Presărați cu susan și ceapă verde proaspătă.\n\n6. Răciți până la 3 ore dacă pregătiți din timp, apoi savurați!",
  "prepTimeMinutes": 15,
  "cookTimeMinutes": 12,
  "servings": 2,
  "mealType": "SNACK",
  "dishCategory": "APPETIZER",
  "ingredients": [
    {
      "name": "Eggs",
      "quantity": 2,
      "unit": "pcs",
      "isStarIngredient": true
    },
    {
      "name": "Mayonnaise",
      "quantity": 30,
      "unit": "ml",
      "isStarIngredient": true
    },
    {
      "name": "Soy Sauce",
      "quantity": 2.5,
      "unit": "ml",
      "isStarIngredient": false
    },
    {
      "name": "Wasabi Paste",
      "quantity": 2.5,
      "unit": "g",
      "isStarIngredient": false
    },
    {
      "name": "Ginger",
      "quantity": 2.5,
      "unit": "g",
      "isStarIngredient": false
    },
    {
      "name": "Rice Vinegar",
      "quantity": 2.5,
      "unit": "ml",
      "isStarIngredient": false
    },
    {
      "name": "Breadcrumbs",
      "quantity": 10,
      "unit": "g",
      "isStarIngredient": false
    },
    {
      "name": "Pretzel Crisps",
      "quantity": 20,
      "unit": "g",
      "isStarIngredient": true
    },
    {
      "name": "Sesame Seeds",
      "quantity": 2.5,
      "unit": "g",
      "isStarIngredient": false
    },
    {
      "name": "Scallion",
      "quantity": 15,
      "unit": "g",
      "isStarIngredient": false
    }
  ],
  "sourceUrl": "https://www.allrecipes.com/recipe/247401/asian-deviled-egg-pretzel-crisps/",
  "cuisine": "Asian",
  "id": "asian_deviled_egg_pretzel_crisps",
  "imageUrl": "recipes/images/asian/asian_deviled_egg_pretzel_crisps.webp"
}