{
  "name": "Азиатский завтрак стир-фрай",
  "instructions": "1. В средней кастрюле доведите воду и киноа до сильного кипения на большом огне. Как только закипит, уменьшите огонь до средне-слабого, накройте плотно прилегающей крышкой и варите на медленном огне, пока киноа не станет мягким и не впитает всю воду, примерно 15-20 минут. Снимите с огня и оставьте под крышкой.\n\n2. Пока киноа готовится, подготовьте овощи. Крупно нарежьте морковь, брокколи и лук, затем измельчите их в кухонном комбайне до мелкой нарезки, но не до состояния пюре, сохраняя некоторую текстуру.\n\n3. Разогрейте кунжутное масло в большой сковороде или воке на среднем огне, пока оно не заблестит. Добавьте измельченный чеснок и обжаривайте, постоянно помешивая, пока он не станет ароматным и слегка золотистым, около 1 минуты. Будьте осторожны, чтобы не сжечь чеснок.\n\n4. Добавьте измельченные овощи в сковороду и готовьте, часто помешивая, пока лук не станет прозрачным, а овощи не начнут размягчаться, примерно 3-5 минут. Добавьте капусту кале и продолжайте готовить, перемешивая все вместе, пока кале не завянет, еще около 1 минуты.\n\n5. Влейте соевый соус и воду, перемешивая для объединения. Дайте смеси готовиться еще 5 минут, позволяя ароматам соединиться, а жидкости слегка выпариться. Добавьте измельченную куриную грудку и приготовленное киноа к овощной смеси, хорошо перемешивая для равномерного распределения. Готовьте, пока все не прогреется, примерно 2-3 минуты.\n\n6. Переложите смесь стир-фрай на сервировочные тарелки. Слегка сбрызните ту же сковороду кулинарным спреем и верните на средний огонь. Разбейте яйца в сковороду и приготовьте их по вашему предпочтению—глазунья, перевернутые или омлет—примерно 3-5 минут в зависимости от желаемой степени готовности.\n\n7. Аккуратно положите приготовленные яйца поверх стир-фрая на каждой тарелке. При желании полейте чили-чесночным соусом, посыпьте свежими листьями кинзы и завершите щедрой порцией кунжутных семян для дополнительного аромата и хруста. Подавайте немедленно, пока горячее.",
  "simpleInstructions": "1. Сварите киноа в воде до мягкости и пышности.\n\n2. Измельчите овощи в комбайне до мелкой нарезки.\n\n3. Разогрейте кунжутное масло, затем обжарьте чеснок до аромата и золотистости.\n\n4. Добавьте овощи и готовьте до размягчения, затем завяльте кале.\n\n5. Влейте соевый соус и воду, затем перемешайте курицу и киноа до прогрева.\n\n6. Приготовьте яйца по вашему вкусу на той же сковороде.\n\n7. Выложите яйца на стир-фрай, украсьте соусом, кинзой и кунжутом, и наслаждайтесь!",
  "prepTimeMinutes": 20,
  "cookTimeMinutes": 35,
  "servings": 2,
  "mealType": "BREAKFAST",
  "dishCategory": "MAIN_COURSE",
  "ingredients": [
    {
      "name": "Water",
      "quantity": 250,
      "unit": "ml",
      "isStarIngredient": false
    },
    {
      "name": "Quinoa",
      "quantity": 60,
      "unit": "g",
      "isStarIngredient": true
    },
    {
      "name": "Carrot",
      "quantity": 100,
      "unit": "g",
      "isStarIngredient": false
    },
    {
      "name": "Broccoli",
      "quantity": 100,
      "unit": "g",
      "isStarIngredient": false
    },
    {
      "name": "Onion",
      "quantity": 50,
      "unit": "g",
      "isStarIngredient": false
    },
    {
      "name": "Sesame Oil",
      "quantity": 25,
      "unit": "ml",
      "isStarIngredient": false
    },
    {
      "name": "Garlic",
      "quantity": 20,
      "unit": "g",
      "isStarIngredient": false
    },
    {
      "name": "Kale",
      "quantity": 60,
      "unit": "g",
      "isStarIngredient": false
    },
    {
      "name": "Soy Sauce",
      "quantity": 25,
      "unit": "ml",
      "isStarIngredient": false
    },
    {
      "name": "Chicken Breast",
      "quantity": 100,
      "unit": "g",
      "isStarIngredient": true
    },
    {
      "name": "Eggs",
      "quantity": 4,
      "unit": "pcs",
      "isStarIngredient": true
    },
    {
      "name": "Sriracha",
      "quantity": 10,
      "unit": "ml",
      "isStarIngredient": false
    },
    {
      "name": "Fresh Cilantro",
      "quantity": 10,
      "unit": "g",
      "isStarIngredient": false
    },
    {
      "name": "Sesame Seeds",
      "quantity": 10,
      "unit": "g",
      "isStarIngredient": false
    }
  ],
  "sourceUrl": "https://www.allrecipes.com/recipe/265277/asian-breakfast-stir-fry/",
  "cuisine": "Asian",
  "id": "asian_breakfast_stir_fry",
  "imageUrl": "recipes/images/asian/asian_breakfast_stir_fry.webp"
}